ShiyanlouRJiaochengHeji20160904/README.md
ShiyanlouRJiaochengHeji20160904/__init__.py
ShiyanlouRJiaochengHeji20160904/__main__.py
ShiyanlouRJiaochengHeji20160904/file.epub
ShiyanlouRJiaochengHeji20160904/index.html
ShiyanlouRJiaochengHeji20160904/css/__init__.py
ShiyanlouRJiaochengHeji20160904/css/annotations.css
ShiyanlouRJiaochengHeji20160904/css/main.css
ShiyanlouRJiaochengHeji20160904/css/normalize.css
ShiyanlouRJiaochengHeji20160904/css/popup.css
ShiyanlouRJiaochengHeji20160904/font/__init__.py
ShiyanlouRJiaochengHeji20160904/font/fontello.eot
ShiyanlouRJiaochengHeji20160904/font/fontello.svg
ShiyanlouRJiaochengHeji20160904/font/fontello.ttf
ShiyanlouRJiaochengHeji20160904/font/fontello.woff
ShiyanlouRJiaochengHeji20160904/img/__init__.py
ShiyanlouRJiaochengHeji20160904/img/annotator-glyph-sprite.png
ShiyanlouRJiaochengHeji20160904/img/annotator-icon-sprite.png
ShiyanlouRJiaochengHeji20160904/img/apple-touch-icon.png
ShiyanlouRJiaochengHeji20160904/img/cancelfullscreen.png
ShiyanlouRJiaochengHeji20160904/img/close.png
ShiyanlouRJiaochengHeji20160904/img/fullscreen.png
ShiyanlouRJiaochengHeji20160904/img/loader.gif
ShiyanlouRJiaochengHeji20160904/img/menu-icon.png
ShiyanlouRJiaochengHeji20160904/img/save.png
ShiyanlouRJiaochengHeji20160904/img/saved.png
ShiyanlouRJiaochengHeji20160904/img/settings-s.png
ShiyanlouRJiaochengHeji20160904/img/settings.png
ShiyanlouRJiaochengHeji20160904/img/star.png
ShiyanlouRJiaochengHeji20160904/js/__init__.py
ShiyanlouRJiaochengHeji20160904/js/epub.js
ShiyanlouRJiaochengHeji20160904/js/epub.min.js
ShiyanlouRJiaochengHeji20160904/js/epub.min.map
ShiyanlouRJiaochengHeji20160904/js/hooks.min.js
ShiyanlouRJiaochengHeji20160904/js/hooks.min.map
ShiyanlouRJiaochengHeji20160904/js/reader.js
ShiyanlouRJiaochengHeji20160904/js/reader.js.map
ShiyanlouRJiaochengHeji20160904/js/reader.min.js
ShiyanlouRJiaochengHeji20160904/js/reader.min.map
ShiyanlouRJiaochengHeji20160904/js/hooks/__init__.py
shiyanlou_r_jiaocheng_heji_20160904-2024.3.2.0.dist-info/METADATA
shiyanlou_r_jiaocheng_heji_20160904-2024.3.2.0.dist-info/WHEEL
shiyanlou_r_jiaocheng_heji_20160904-2024.3.2.0.dist-info/entry_points.txt
shiyanlou_r_jiaocheng_heji_20160904-2024.3.2.0.dist-info/top_level.txt
shiyanlou_r_jiaocheng_heji_20160904-2024.3.2.0.dist-info/RECORD
